deng/__init__.py
deng/addressinfo.py
deng/baidu.py
deng/bankinfo.py
deng/cache.py
deng/colors.py
deng/db_oper.py
deng/encrypt.py
deng/feishu.py
deng/file.py
deng/flow.py
deng/git.py
deng/gitea.py
deng/github.py
deng/image.py
deng/message.py
deng/my_http.py
deng/net.py
deng/samba.py
deng/singleton.py
deng/testdata.py
deng/time.py
deng/utils.py
deng/windows.py
deng-2025.10.11.1.dist-info/METADATA
deng-2025.10.11.1.dist-info/WHEEL
deng-2025.10.11.1.dist-info/top_level.txt
deng-2025.10.11.1.dist-info/RECORD
