Metadata-Version: 2.4
Name: deng
Version: 2025.10.11.1
Summary: Personal method encapsulation
Home-page: https://github.com/Deng2016/deng
Author: dengqingyong
Author-email: yu12377@163.com
Classifier: Programming Language :: Python
Classifier: Programming Language :: Python :: Implementation
Classifier: Programming Language :: Python :: 3.7
Classifier: Programming Language :: Python :: 3.8
Classifier: Programming Language :: Python :: 3.9
Classifier: Programming Language :: Python :: 3.10
Classifier: Programming Language :: Python :: 3.11
Classifier: Programming Language :: Python :: 3.12
Classifier: Programming Language :: Python :: 3.13
Classifier: Topic :: Software Development :: Libraries
Requires-Dist: requests>=2.26.0
Requires-Dist: redis>=4.5.0
Requires-Dist: pycryptodome>=3.15.0
Requires-Dist: xpinyin>=0.7.6
Requires-Dist: pysmb>=1.2.10
Requires-Dist: pyjwt>=2.8.0
Requires-Dist: pytz>=2025.2
Requires-Dist: pymysql>=1.0.0
Dynamic: author
Dynamic: author-email
Dynamic: classifier
Dynamic: description
Dynamic: description-content-type
Dynamic: home-page
Dynamic: requires-dist
Dynamic: summary
